{
  "title": "Patent Journal special notices: 7104",
  "body": "\"These are notices which appear for a limited number of weeks.  They include Intellectual Property policy announcements and recent additions to the British Library.  There are no new policy announcements from the Intellectual Property Office or notification of recent additions to the British Library to appear in this edition of the Patents Journal special notices for journal 7104.  Further information on Patents Journal special notices is available. \"",
  "base_path": "/government/publications/patent-journal-special-notice-7104",
  "taxons": [
    {
      "title": "Patents",
      "base_path": "/business/patents"
    }
  ]
}