{
  "title": "Assessing the legal and economic implications of the Employment Rights Act 2025",
  "body": "\"This paper evaluates the legal and economic implications of the Employment Rights Act 2025. The paper:   analyses the impact of the act on UK labour law and the wider economy compares UK protections with those in other Organisation for Economic Co-operation and Development (OECD) countries evaluates potential effects on employment and productivity   \"",
  "base_path": "/government/publications/assessing-the-legal-and-economic-implications-of-the-employment-rights-act-2025",
  "taxons": [
    {
      "title": "Labour market reform",
      "base_path": "/employment/labour-market-reform"
    }
  ]
}