{
  "title": "Clean Heat Market Mechanism: who it applies to, annual tasks",
  "body": "\"The CHMM supports the development of low-carbon electric heat pumps. It places an obligation on manufacturers supplying gas and oil boilers in the UK market.  Manufacturers must meet targets for the installation of heat pumps in existing properties in proportion to their qualifying sales of fossil fuel boilers. Manufacturers can do this by supplying heat pumps themselves or by getting credits from other manufacturers.  The scheme runs from 1 April 2025 until at least 2029 and applies to the whole of the UK. The Environment Agency is the scheme administrator.  The Clean Heat Market Mechanism Regulations 2025 (the CHMM Regulations) set out the obligations of the scheme.  The Energy Act 2023, Part 4, Chapter 1 is the primary legislation underpinning the scheme.  Who the scheme applies to  The CHMM applies to your business if you both:   manufacture or have someone to manufacture fossil fuel boilers or heat pumps for you own the right to use the brand name, trademark or other distinctive mark used to market fossil fuel boilers or heat pumps in the UK    If the CHMM applies to you and you do not comply with the CHMM Regulations, you may face enforcement action. This could be a civil penalty or criminal prosecution.   The CHMM has 3 categories of ‘undertakings’, which one applies to you will depend on the activities your business carries out and the extent of these activities. It will also depend on the size of your organisation.  Scheme participants  A scheme participant is a company or a group of companies that, in a relevant sales year, supplies on or for the UK market either:   20,000 or more gas boilers (capable of burning natural gas or liquified petroleum gas) 1,000 or more oil boilers   You’re not a scheme participant if you’re a small company or group as defined in the Companies Act 2006.  Scheme participants must register with the CHMM scheme, and the Environment Agency will record their low carbon heat target in the registry.  If a scheme participant is also a supplier of heat pumps, they are a scheme participant and not a credit holder. In these cases, any CHMM credits go to the scheme participant’s account alongside their obligated target. There is no need for them to create a separate account.  Near-threshold suppliers  A near-threshold supplier is a company or group of companies that, in a relevant sales year, supplies on or for the UK market:   between 15,000 and 19,999 gas boilers (capable of burning natural gas or liquified petroleum gas) between 750 and 999 oil boilers   You’re not a near-threshold supplier if you’re a small company or group as defined in the Companies Act 2006.  If a company’s (or group of companies’) gas and oil boiler sales are greater than these thresholds, they will become a scheme participant instead.  Near-threshold suppliers must register with the CHMM scheme. They also need to fulfil specific reporting requirements. They will not have a low-carbon heat target and associated obligation.  A near-threshold supplier who also supplies heat pumps is...",
  "base_path": "/guidance/clean-heat-market-mechanism-who-it-applies-to-annual-tasks",
  "taxons": [
    {
      "title": "Energy efficiency",
      "base_path": "/environment/climate-change-energy-energy-efficiency"
    },
    {
      "title": "Low carbon technologies",
      "base_path": "/environment/low-carbon-technologies"
    },
    {
      "title": "Business regulation",
      "base_path": "/business-and-industry/business-regulation"
    }
  ]
}