{
  "title": "Landmark plan to rebuild NHS in working-class communities",
  "body": "\" Billions freed up to move critical resources like medicines and equipment to regions that most need them Major changes to how GP funding is distributed to help working-class communities and coastal areas Health Secretary to speak in Blackpool on 10 Year Health Plan’s focus on closing health inequalities   People living in working-class communities and areas where medical resources are desperately needed are set to benefit from a huge boost in support, with billions of pounds diverted to deprived areas, as the government’s 10 Year Health Plan takes unprecedented action to tackle the nation’s stark health inequalities.    After years of neglect, areas where people need the NHS most often have the fewest GPs, the worst performing services and the longest waits - a phenomenon dubbed the ‘inverse care law’. People in working-class areas and coastal towns spend more of their lives in ill health, and life expectancy among women with the lowest incomes has fallen in recent years, after decades of progress.  The 10 Year Health Plan will set out how the government plans to rebuild the NHS and tackle widening inequalities in people’s health through fundamental reforms to our health system, putting an end to a postcode lottery of care.  In recent months, the NHS has driven trusts and integrated care boards (ICBs) hard to cut out wasteful spending and tackle projected deficits. By driving out the culture of deficits, around £2.2 billion previously set aside for deficit support will be freed up, so it can be reinvested in critical resources like staff, medicines, new technology and equipment where they are most needed. This will support millions of people in parts of England that have historically been left behind, such as in rural communities, coastal towns and working-class communities.  The Health Secretary will announce the change during a speech in the North West.  Speaking in the North West today [25 June], Health and Social Care Secretary, Wes Streeting, is expected to say:   The truth is, those in greatest need often receive the worst quality healthcare. It flies in the face of the values the NHS was founded on. The circumstances of your birth shouldn’t determine your worth. A core ambition of our 10 Year Plan will be to restore the promise of the NHS, to provide first class healthcare for everyone in our country and end the postcode lottery.  Last year we sent crack teams of top clinicians to hospitals in parts of the country with the highest waiting lists and levels of economic inactivity. It has seen waiting lists in those areas falling twice as fast as the rest of the country, helping get sick Brits back to health and back to work.  Thanks to the reforms we’ve made to bear down on wasteful spending, we can now invest the savings in working-class communities that need it most. Where towns have the greatest health needs and the fewest GPs, we will prioritise investment to rebuild your NHS and rebuild the health of your community.    Over the past...",
  "base_path": "/government/news/landmark-plan-to-rebuild-nhs-in-working-class-communities",
  "taxons": [
    {
      "title": "National Health Service",
      "base_path": "/health-and-social-care/national-health-service"
    }
  ]
}