{
  "title": "Hay fever and airborne allergens",
  "body": "\"  CCHS navigation menu:  CCHS homepageTopic: environmental exposures Air-related exposure: airborne allergensPart of: The Health Risks of Airborne Allergens    Key resources for Hay fever and airborne allergens:    Hay Fever and Airborne Allergens    Allergic Rhinitis and Hey Fever - Allergy UK   Pollen forecast - Met Office    Hay Fever - Met Office   Hay Fever - NHS   Allergic rhinitis - NHS    More content:   Prevention and coping with airborne allergens    About hay fever  Allergic rhinitis, more commonly known as hay fever, is an allergy caused by pollen, house dust mite or pet hair and skin ‚Äã(1)‚Äã with common symptoms including:   sneezing coughing runny or blocked nose itchy eyes, mouth or throat ‚Äã(2)‚Äã   Hay fever is very common, with cases having trebled in the last 20 years. It affects 10 to 15% of children and 26% of adults in the UK ‚Äã(1)‚Äã. Hay fever normally develops during childhood or as a teenager, but can be triggered at any age.¬ÝYou are more likely to suffer from hay fever if you also suffer from eczema or asthma (1).  Although it is sometimes regarded as a small problem, hay fever causes disruption to sleep, which impacts daytime concentration, and causes people to miss days of work or school (1). People who have hay fever are also at an increased risk of developing asthma, highlighting the importance of treating this condition. For people who are allergic to pollen, it‚Äôs also worth knowing that certain things can worsen the effects of pollen, such as alcohol. Pollen levels can also be higher after rainfall if it is followed by dry weather ‚Äã(3)‚Äã.  Factors that impact pollen concentration  Pollen is a fine powder made up of tiny particles released by plants and trees and spread by insects and the wind ‚Äã(5).‚Äã It can be inhaled by people and animals, and causes irritation and inflammation for those who are allergic to it ‚Äã(5)‚Äã. Birch pollen is the most dominant tree pollen in Northern and Central Europe and is a major cause of hay fever and, possibly, asthma symptoms ‚Äã(6)‚Äã.  Within the pollen season, different types of allergens peak at different times:   tree pollens occur first from March until mid-May¬Ý grass pollen then occurs from mid-May until July (this is the most common hay fever trigger)¬Ý weed pollen can be released at any time but most typically the season occurs from the end of June until September (7)‚Äã   Pollen seasons can be affected by many different factors, including where you are in the UK. For example, the pollen season is shorter and starts later in the North of the UK, and urban and coastal areas have lower counts than rural areas and inland locations.  Low winter temperatures can delay the season start because trees and plants that produce pollen remain dormant for longer. If there is not a lot of rain during spring then this can also reduce the amount of pollen produced. Rainfall generally causes a decrease in pollen concentrations, however, if rainfall is early in the day as well as heavy and...",
  "base_path": "/guidance/hay-fever-and-airborne-allergens",
  "taxons": [
    {
      "title": "Pollution and environmental quality",
      "base_path": "/environment/pollution-and-environmental-quality"
    }
  ]
}