{
  "title": "The Crown Estate annual report and accounts 2024 to 2025",
  "body": "\"This is the organisation’s 13th integrated report – a concise communication about how the organisation has created value in the short, medium and long term. The document provides information for stakeholders to assess its performance, business model and strategy. \"",
  "base_path": "/government/publications/the-crown-estate-annual-report-and-accounts-2024-to-2025",
  "taxons": [
    {
      "title": "Government efficiency, transparency and accountability",
      "base_path": "/government/government-efficiency-transparency-and-accountability"
    }
  ]
}