{
  "title": "بيان ختامي مشترك بشأن الدعم الدولي لحكومة اليمن",
  "body": "\"في 20 يناير، زار وزير شؤون الشرق الأوسط وشمال أفريقيا الأمم المتحدة للدعوة إلى التطبيق الكامل لاتفاق وقف إطلاق النار بين إسرائيل وحماس. كما أطلق مبادرة بقيادة بريطانية لتقديم دعم مالي وسياسي لمستقبل اليمن.  هذه المبادرة، تشمل صندوق المساعدة الفنية لليمن، وتجمع أعضاء من المجتمع الدولي لدعم الحوكمة في اليمن.  وهذه الورقة هي بيان ختامي مشترك بريطاني-يمني صدر عن اجتماع استضافه البلدان لحشد الدعم الدولي للحكومة اليمنية.  اقرأ البيان الصحفي ذي الصلة: وقف إطلاق النار ’بارقة أمل‘ كما قال وزير شؤون الشرق الأوسط في الأمم المتحدة \"",
  "base_path": "/government/publications/support-for-the-government-of-yemen-joint-communique.ar",
  "taxons": [
    {
      "title": "Peace and stability in the Middle East and North Africa",
      "base_path": "/international/peace-stability-in-me-and-north-africa"
    },
    {
      "title": "Governance in developing countries",
      "base_path": "/international/governance-in-developing-countries"
    }
  ]
}