{
  "title": "Independent review of physician associates and anaesthesia associates: areas to be covered",
  "body": "\"This document sets out further details to the terms of reference for the independent review of the physician associate and anaesthesia associate professions that has been commissioned by the Secretary of State for Health and Social Care.  The review will consider the safety of the roles and their contribution to multidisciplinary healthcare teams. It will be led by Professor Gillian Leng CBE.  The conclusions of the review will help to inform the refreshed workforce plan that the government has committed to publish in summer 2025 and wider government policy. \"",
  "base_path": "/government/publications/independent-review-of-physician-and-anaesthesia-associates-areas-to-be-covered",
  "taxons": [
    {
      "title": "Health workforce",
      "base_path": "/health-and-social-care/health-workforce"
    },
    {
      "title": "Patient safety",
      "base_path": "/health-and-social-care/patient-safety"
    }
  ]
}