{
  "title": "SLC Annual Report and Accounts 2024 to 2025",
  "body": "\"Our annual report gives details of what we have done, how we performed and how that performance was measured during the reporting period.  Filed with Companies House on 24 July 2025 and also available at Student Loans Company filing history \"",
  "base_path": "/government/publications/slc-annual-report-and-accounts-2024-to-2025",
  "taxons": [
    {
      "title": "Student loans",
      "base_path": "/education/student-loans-bursaries-and-sponsorship"
    }
  ]
}