{
  "title": "Nationalising the water sector: how we assessed the cost",
  "body": "\"The Department for Environment, Food and Rural Affairs (Defra) has estimated that the current cost of nationalising the water industry would be around £100 billion. Other commentators have published alternative figures.  This technical note details the assumptions and approach that Defra has taken to reach its estimate.  \"",
  "base_path": "/government/publications/nationalising-the-water-sector-how-we-assessed-the-cost",
  "taxons": [
    {
      "title": "Water and sewerage services",
      "base_path": "/environment/water-and-sewerage-services"
    },
    {
      "title": "Water quality",
      "base_path": "/business/environmental-management-water-water-quality"
    }
  ]
}